Metadata-Version: 1.1
Name: rofa
Version: 0.1.2
Summary: **Rofa ** is abbreviation for Robust Factor
Home-page: https://github.com/sjquant/rofa
Author: SJQuant
Author-email: seonujang92@gmail.com
License: MIT
Keywords: quant,investment,factor investing,backtest
Platform: UNKNOWN
Classifier: Programming Language :: Python :: 3
Classifier: License :: OSI Approved :: MIT License
Classifier: Operating System :: OS Independent
